README
setup.py
fantasy_tracker.egg-info/PKG-INFO
fantasy_tracker.egg-info/SOURCES.txt
fantasy_tracker.egg-info/dependency_links.txt
fantasy_tracker.egg-info/not-zip-safe
fantasy_tracker.egg-info/requires.txt
fantasy_tracker.egg-info/top_level.txt
ftracker/__init__.py
ftracker/yahoo.py
scripts/fantasy_stats