Metadata-Version: 1.0
Name: fantasy-tracker
Version: 0.2
Summary: Library to fetch Fantasy Football statistics
Home-page: http://github.com/matburt/fantasy-tracker
Author: Matthew W. Jones
Author-email: mat@matburt.net
License: BSD
Platform: UNKNOWN
